FinalTuringAPI/__init__.py
FinalTuringAPI-1.0.0.dist-info/LICENSE
FinalTuringAPI-1.0.0.dist-info/METADATA
FinalTuringAPI-1.0.0.dist-info/WHEEL
FinalTuringAPI-1.0.0.dist-info/top_level.txt
FinalTuringAPI-1.0.0.dist-info/RECORD
