Metadata-Version: 2.1
Name: FinalTuringAPI
Version: 1.0.0
Summary: The API framework for IcodeYoudao.
Author: xbzstudio
Author-email: mmmhss2022@outlook.com
License: MIT Licence
Project-URL: Homepage, https://github.com/xbzstudio/TuringAPI
Project-URL: Documentation, https://xbz-studio.gitbook.io/turingapi/
Classifier: Programming Language :: Python :: 3.10
Classifier: Programming Language :: Python :: 3.11
Classifier: Programming Language :: Python :: 3.12
Classifier: License :: OSI Approved :: MIT License
Classifier: Development Status :: 5 - Production/Stable
Classifier: Topic :: Software Development :: Build Tools
Classifier: Intended Audience :: Developers
Requires-Python: >=3.10
License-File: LICENSE
Requires-Dist: urllib3 >=2.0.7
